tytorch/__init__.py
tytorch/dataset.py
tytorch/metrics.py
tytorch/trainer.py
tytorch/datapipeline/base.py
tytorch/datapipeline/global_transform_strategies.py
tytorch/datapipeline/item_transform_strategies.py
tytorch/datapipeline/loader_strategies.py
tytorch/examples/autoencoder/find_similar_embeddings.py
tytorch/examples/autoencoder/generate_test_embeddings.py
tytorch/examples/autoencoder/sharpen.py
tytorch/examples/autoencoder/train_autoencoder.py
tytorch/examples/autoencoder/utils.py
tytorch/examples/autoencoder/visualize_latent_space.py
tytorch/examples/classification/image/flowers/train.py
tytorch/examples/classification/image/flowers/tune.py
tytorch/examples/classification/sequence/gestures/train.py
tytorch/examples/classification/sequence/gestures/tune.py
tytorch/examples/timeseriesforecasting/sunspots/train.py
tytorch/utils/data.py
tytorch/utils/mlflow.py
tytorch/utils/trainer_utils.py
tytorch-0.8.8.dist-info/METADATA
tytorch-0.8.8.dist-info/WHEEL
tytorch-0.8.8.dist-info/RECORD
